{"cameraMode":{"drawMode":0,"name":"Shaded","section":"Shading Mode"},"sceneLighting":true,"audioPlay":false,"sceneViewState":{"m_AlwaysRefresh":false,"showFog":true,"showSkybox":true,"showFlares":true,"showImageEffects":true,"showParticleSystems":true,"showVisualEffectGraphs":true,"m_FxEnabled":true},"in2DMode":false,"pivot":{"x":2.7170135974884035,"y":-0.03999995440244675,"z":9.68863582611084},"rotation":{"x":-0.00975759606808424,"y":-0.8363931179046631,"z":0.014897389337420464,"w":-0.5478507280349731},"size":10.0,"orthographic":false}